graphD/__init__.py
graphD/animation.py
graphD/core.py
graphD/interactive.py
graphD/renderer.py
graphD/stats.py
graphD/subplot.py
graphD/visualizations.py
graphd-0.2.0.dist-info/licenses/LICENSE
graphd-0.2.0.dist-info/METADATA
graphd-0.2.0.dist-info/WHEEL
graphd-0.2.0.dist-info/top_level.txt
graphd-0.2.0.dist-info/RECORD
