Metadata-Version: 2.4
Name: graphD
Version: 0.2.0
Summary: A Python library for drawing graphs from scratch.
Author-email: ghwst-point <pocox6prohypeee@gmail.com>
Project-URL: Homepage, https://github.com/ghwst-point/graphD
Project-URL: Bug Tracker, https://github.com/ghwst-point/graphD/issues
Classifier: Programming Language :: Python :: 3
Classifier: License :: OSI Approved :: MIT License
Classifier: Operating System :: OS Independent
Classifier: Development Status :: 3 - Alpha
Classifier: Intended Audience :: Developers
Classifier: Topic :: Scientific/Engineering :: Visualization
Requires-Python: >=3.7
License-File: LICENSE
Dynamic: license-file
